myipaddress/__init__.py
myipaddress-1.0.2.dist-info/LICENCE
myipaddress-1.0.2.dist-info/METADATA
myipaddress-1.0.2.dist-info/WHEEL
myipaddress-1.0.2.dist-info/top_level.txt
myipaddress-1.0.2.dist-info/RECORD
